Workbook

Sheet Assumptions
A1: NAIA — Financial Model — Assumptions
A2: Commission-marketplace model: NAIA charges clinics a % of each completed booking (Airbnb-style take rate). Edit the blue cells; everything else calculates.
A4: REVENUE DRIVERS
A5: Average procedure value (£) | B5: 3000 | C5: Blended avg across procedures/destinations
A6: Commission / take rate (%) | B6: 0.15 | C6: What NAIA charges the clinic per booking
A7: Revenue per booking (£) | B7: =B5*B6 -> 450 | C7: procedure value × take rate
A8: MARKETPLACE GROWTH
A9: Starting active clinics (month 1) | B9: 3
A10: New clinics added / month | B10: 2 | C10: Linear supply growth (edit to model faster/slower)
A11: Bookings per clinic / month | B11: 2 | C11: Avg completed bookings each active clinic drives
A12: COSTS
A13: Variable ops cost / booking (£) | B13: 60 | C13: Payment fees + coordination per booking
A14: Customer acquisition cost / booking (£) | B14: 150 | C14: Marketing spend to generate one booking
A15: Fixed opex / month — Year 1 (£) | B15: 12000 | C15: Team, tools, overhead
A16: Fixed opex / month — Year 2 (£) | B16: 22000
A17: Fixed opex / month — Year 3 (£) | B17: 32000
A19: Contribution per booking (£) | B19: =B7-B13-B14 -> 240
A20: Contribution margin (%) | B20: =B19/B7 -> 0.53333333
A22: Blue = editable input · Black = calculated. Model assumes clinics pay commission; patients are not charged a fee (change take rate to test).

Sheet Monthly Model
A1: NAIA — 36-Month Projection
A3: Month | B3: Year | C3: Active clinics | D3: Bookings /clinic | E3: Total bookings | F3: Commission revenue (£) | G3: Ops cost (£) | H3: Marketing / CAC (£) | I3: Contribution (£) | J3: Fixed opex (£) | K3: Net profit (£) | L3: Cumulative net (£) | M3: 1st-profit flag
A4: 1 | B4: =INT((A4-1)/12)+1 -> 1 | C4: =Assumptions!$B$9 -> 3 | D4: =Assumptions!$B$11 -> 2 | E4: =C4*D4 -> 6 | F4: =E4*Assumptions!$B$7 -> 2700 | G4: =E4*Assumptions!$B$13 -> 360 | H4: =E4*Assumptions!$B$14 -> 900 | I4: =F4-G4-H4 -> 1440 | J4: =CHOOSE(B4,Assumptions!$B$15,Assumptions!$B$16,Assumptions!$B$17) -> 12000 | K4: =I4-J4 -> -10560 | L4: =K4 -> -10560 | M4: =IF(K4>0,A4,"")
A5: 2 | B5: =INT((A5-1)/12)+1 -> 1 | C5: =C4+Assumptions!$B$10 -> 5 | D5: =Assumptions!$B$11 -> 2 | E5: =C5*D5 -> 10 | F5: =E5*Assumptions!$B$7 -> 4500 | G5: =E5*Assumptions!$B$13 -> 600 | H5: =E5*Assumptions!$B$14 -> 1500 | I5: =F5-G5-H5 -> 2400 | J5: =CHOOSE(B5,Assumptions!$B$15,Assumptions!$B$16,Assumptions!$B$17) -> 12000 | K5: =I5-J5 -> -9600 | L5: =L4+K5 -> -20160 | M5: =IF(K5>0,A5,"")
A6: 3 | B6: =INT((A6-1)/12)+1 -> 1 | C6: =C5+Assumptions!$B$10 -> 7 | D6: =Assumptions!$B$11 -> 2 | E6: =C6*D6 -> 14 | F6: =E6*Assumptions!$B$7 -> 6300 | G6: =E6*Assumptions!$B$13 -> 840 | H6: =E6*Assumptions!$B$14 -> 2100 | I6: =F6-G6-H6 -> 3360 | J6: =CHOOSE(B6,Assumptions!$B$15,Assumptions!$B$16,Assumptions!$B$17) -> 12000 | K6: =I6-J6 -> -8640 | L6: =L5+K6 -> -28800 | M6: =IF(K6>0,A6,"")
A7: 4 | B7: =INT((A7-1)/12)+1 -> 1 | C7: =C6+Assumptions!$B$10 -> 9 | D7: =Assumptions!$B$11 -> 2 | E7: =C7*D7 -> 18 | F7: =E7*Assumptions!$B$7 -> 8100 | G7: =E7*Assumptions!$B$13 -> 1080 | H7: =E7*Assumptions!$B$14 -> 2700 | I7: =F7-G7-H7 -> 4320 | J7: =CHOOSE(B7,Assumptions!$B$15,Assumptions!$B$16,Assumptions!$B$17) -> 12000 | K7: =I7-J7 -> -7680 | L7: =L6+K7 -> -36480 | M7: =IF(K7>0,A7,"")
A8: 5 | B8: =INT((A8-1)/12)+1 -> 1 | C8: =C7+Assumptions!$B$10 -> 11 | D8: =Assumptions!$B$11 -> 2 | E8: =C8*D8 -> 22 | F8: =E8*Assumptions!$B$7 -> 9900 | G8: =E8*Assumptions!$B$13 -> 1320 | H8: =E8*Assumptions!$B$14 -> 3300 | I8: =F8-G8-H8 -> 5280 | J8: =CHOOSE(B8,Assumptions!$B$15,Assumptions!$B$16,Assumptions!$B$17) -> 12000 | K8: =I8-J8 -> -6720 | L8: =L7+K8 -> -43200 | M8: =IF(K8>0,A8,"")
A9: 6 | B9: =INT((A9-1)/12)+1 -> 1 | C9: =C8+Assumptions!$B$10 -> 13 | D9: =Assumptions!$B$11 -> 2 | E9: =C9*D9 -> 26 | F9: =E9*Assumptions!$B$7 -> 11700 | G9: =E9*Assumptions!$B$13 -> 1560 | H9: =E9*Assumptions!$B$14 -> 3900 | I9: =F9-G9-H9 -> 6240 | J9: =CHOOSE(B9,Assumptions!$B$15,Assumptions!$B$16,Assumptions!$B$17) -> 12000 | K9: =I9-J9 -> -5760 | L9: =L8+K9 -> -48960 | M9: =IF(K9>0,A9,"")
A10: 7 | B10: =INT((A10-1)/12)+1 -> 1 | C10: =C9+Assumptions!$B$10 -> 15 | D10: =Assumptions!$B$11 -> 2 | E10: =C10*D10 -> 30 | F10: =E10*Assumptions!$B$7 -> 13500 | G10: =E10*Assumptions!$B$13 -> 1800 | H10: =E10*Assumptions!$B$14 -> 4500 | I10: =F10-G10-H10 -> 7200 | J10: =CHOOSE(B10,Assumptions!$B$15,Assumptions!$B$16,Assumptions!$B$17) -> 12000 | K10: =I10-J10 -> -4800 | L10: =L9+K10 -> -53760 | M10: =IF(K10>0,A10,"")
A11: 8 | B11: =INT((A11-1)/12)+1 -> 1 | C11: =C10+Assumptions!$B$10 -> 17 | D11: =Assumptions!$B$11 -> 2 | E11: =C11*D11 -> 34 | F11: =E11*Assumptions!$B$7 -> 15300 | G11: =E11*Assumptions!$B$13 -> 2040 | H11: =E11*Assumptions!$B$14 -> 5100 | I11: =F11-G11-H11 -> 8160 | J11: =CHOOSE(B11,Assumptions!$B$15,Assumptions!$B$16,Assumptions!$B$17) -> 12000 | K11: =I11-J11 -> -3840 | L11: =L10+K11 -> -57600 | M11: =IF(K11>0,A11,"")
A12: 9 | B12: =INT((A12-1)/12)+1 -> 1 | C12: =C11+Assumptions!$B$10 -> 19 | D12: =Assumptions!$B$11 -> 2 | E12: =C12*D12 -> 38 | F12: =E12*Assumptions!$B$7 -> 17100 | G12: =E12*Assumptions!$B$13 -> 2280 | H12: =E12*Assumptions!$B$14 -> 5700 | I12: =F12-G12-H12 -> 9120 | J12: =CHOOSE(B12,Assumptions!$B$15,Assumptions!$B$16,Assumptions!$B$17) -> 12000 | K12: =I12-J12 -> -2880 | L12: =L11+K12 -> -60480 | M12: =IF(K12>0,A12,"")
A13: 10 | B13: =INT((A13-1)/12)+1 -> 1 | C13: =C12+Assumptions!$B$10 -> 21 | D13: =Assumptions!$B$11 -> 2 | E13: =C13*D13 -> 42 | F13: =E13*Assumptions!$B$7 -> 18900 | G13: =E13*Assumptions!$B$13 -> 2520 | H13: =E13*Assumptions!$B$14 -> 6300 | I13: =F13-G13-H13 -> 10080 | J13: =CHOOSE(B13,Assumptions!$B$15,Assumptions!$B$16,Assumptions!$B$17) -> 12000 | K13: =I13-J13 -> -1920 | L13: =L12+K13 -> -62400 | M13: =IF(K13>0,A13,"")
A14: 11 | B14: =INT((A14-1)/12)+1 -> 1 | C14: =C13+Assumptions!$B$10 -> 23 | D14: =Assumptions!$B$11 -> 2 | E14: =C14*D14 -> 46 | F14: =E14*Assumptions!$B$7 -> 20700 | G14: =E14*Assumptions!$B$13 -> 2760 | H14: =E14*Assumptions!$B$14 -> 6900 | I14: =F14-G14-H14 -> 11040 | J14: =CHOOSE(B14,Assumptions!$B$15,Assumptions!$B$16,Assumptions!$B$17) -> 12000 | K14: =I14-J14 -> -960 | L14: =L13+K14 -> -63360 | M14: =IF(K14>0,A14,"")
A15: 12 | B15: =INT((A15-1)/12)+1 -> 1 | C15: =C14+Assumptions!$B$10 -> 25 | D15: =Assumptions!$B$11 -> 2 | E15: =C15*D15 -> 50 | F15: =E15*Assumptions!$B$7 -> 22500 | G15: =E15*Assumptions!$B$13 -> 3000 | H15: =E15*Assumptions!$B$14 -> 7500 | I15: =F15-G15-H15 -> 12000 | J15: =CHOOSE(B15,Assumptions!$B$15,Assumptions!$B$16,Assumptions!$B$17) -> 12000 | K15: =I15-J15 -> 0 | L15: =L14+K15 -> -63360 | M15: =IF(K15>0,A15,"")
A16: 13 | B16: =INT((A16-1)/12)+1 -> 2 | C16: =C15+Assumptions!$B$10 -> 27 | D16: =Assumptions!$B$11 -> 2 | E16: =C16*D16 -> 54 | F16: =E16*Assumptions!$B$7 -> 24300 | G16: =E16*Assumptions!$B$13 -> 3240 | H16: =E16*Assumptions!$B$14 -> 8100 | I16: =F16-G16-H16 -> 12960 | J16: =CHOOSE(B16,Assumptions!$B$15,Assumptions!$B$16,Assumptions!$B$17) -> 22000 | K16: =I16-J16 -> -9040 | L16: =L15+K16 -> -72400 | M16: =IF(K16>0,A16,"")
... A39: 36 | B39: =INT((A39-1)/12)+1 -> 3 | C39: =C38+Assumptions!$B$10 -> 73 | D39: =Assumptions!$B$11 -> 2 | E39: =C39*D39 -> 146 | F39: =E39*Assumptions!$B$7 -> 65700 | G39: =E39*Assumptions!$B$13 -> 8760 | H39: =E39*Assumptions!$B$14 -> 21900 | I39: =F39-G39-H39 -> 35040 | J39: =CHOOSE(B39,Assumptions!$B$15,Assumptions!$B$16,Assumptions!$B$17) -> 32000 | K39: =I39-J39 -> 3040 | L39: =L38+K39 -> -135360 | M39: =IF(K39>0,A39,"") -> 36

Sheet Summary
A1: NAIA — Financial Summary
A2: Clinic-commission marketplace · £3,000 avg procedure @ 15% take · 3-year view
A4: Year | B4: Total bookings | C4: Commission revenue (£) | D4: Contribution (£) | E4: Fixed opex (£) | F4: Net profit (£)
A5: Year 1 | B5: =SUMIF('Monthly Model'!$B$4:$B$39,1,'Monthly Model'!$E$4:$E$39) -> 336 | C5: =SUMIF('Monthly Model'!$B$4:$B$39,1,'Monthly Model'!$F$4:$F$39) -> 151200 | D5: =SUMIF('Monthly Model'!$B$4:$B$39,1,'Monthly Model'!$I$4:$I$39) -> 80640 | E5: =SUMIF('Monthly Model'!$B$4:$B$39,1,'Monthly Model'!$J$4:$J$39) -> 144000 | F5: =SUMIF('Monthly Model'!$B$4:$B$39,1,'Monthly Model'!$K$4:$K$39) -> -63360
A6: Year 2 | B6: =SUMIF('Monthly Model'!$B$4:$B$39,2,'Monthly Model'!$E$4:$E$39) -> 912 | C6: =SUMIF('Monthly Model'!$B$4:$B$39,2,'Monthly Model'!$F$4:$F$39) -> 410400 | D6: =SUMIF('Monthly Model'!$B$4:$B$39,2,'Monthly Model'!$I$4:$I$39) -> 218880 | E6: =SUMIF('Monthly Model'!$B$4:$B$39,2,'Monthly Model'!$J$4:$J$39) -> 264000 | F6: =SUMIF('Monthly Model'!$B$4:$B$39,2,'Monthly Model'!$K$4:$K$39) -> -45120
A7: Year 3 | B7: =SUMIF('Monthly Model'!$B$4:$B$39,3,'Monthly Model'!$E$4:$E$39) -> 1488 | C7: =SUMIF('Monthly Model'!$B$4:$B$39,3,'Monthly Model'!$F$4:$F$39) -> 669600 | D7: =SUMIF('Monthly Model'!$B$4:$B$39,3,'Monthly Model'!$I$4:$I$39) -> 357120 | E7: =SUMIF('Monthly Model'!$B$4:$B$39,3,'Monthly Model'!$J$4:$J$39) -> 384000 | F7: =SUMIF('Monthly Model'!$B$4:$B$39,3,'Monthly Model'!$K$4:$K$39) -> -26880
A8: 3-yr total | B8: =SUM(B5:B7) -> 2736 | C8: =SUM(C5:C7) -> 1231200 | D8: =SUM(D5:D7) -> 656640 | E8: =SUM(E5:E7) -> 792000 | F8: =SUM(F5:F7) -> -135360
A10: KEY METRICS
A11: Revenue per booking (£) | B11: =Assumptions!B7 -> 450
A12: Contribution margin (%) | B12: =Assumptions!B20 -> 0.53333333
A13: Year-3 exit revenue run-rate (£/mo) | B13: ='Monthly Model'!F39 -> 65700
A14: First profitable month | B14: =IFERROR(MIN('Monthly Model'!M4:M39),"beyond 36m") -> 23
A15: Peak cumulative cash need (£) | B15: =MAX(0,-MIN('Monthly Model'!L4:L39)) -> 141760
A16: Total bookings (3 yrs) | B16: =B8 -> 2736
