Workbook

Sheet Assumptions
A1: NAIA — Business Model Comparison — Assumptions
A2: Same clinic & booking ramp drives all three models, so differences are purely the revenue model. Costs held constant to isolate that effect. Edit blue cells.
A4: SHARED GROWTH DRIVERS
A5: Starting active clinics (month 1) | B5: 3
A6: New clinics added / month | B6: 2
A7: Bookings per clinic / month | B7: 2
A8: SHARED COSTS
A9: Ops cost / booking (£) | B9: 60
A10: CAC / booking (£) | B10: 150 | C10: NAIA drives demand in all models
A11: Fixed opex / month — Year 1 (£) | B11: 12000
A12: Fixed opex / month — Year 2 (£) | B12: 22000
A13: Fixed opex / month — Year 3 (£) | B13: 32000
A14: MODEL 1 — COMMISSION (Airbnb)
A15: Average procedure value (£) | B15: 3000
A16: Commission / take rate (%) | B16: 0.15
A17: Revenue per booking (£) | B17: =B15*B16 -> 450
A18: MODEL 2 — SUBSCRIPTION (Unni)
A19: Subscription fee / clinic / month (£) | B19: 600 | C19: Must cover demand-gen; ~Unni ≈ $730/mo
A20: MODEL 3 — HYBRID
A21: Subscription / clinic / month (£) | B21: 200
A22: Performance / marketing fee (%) | B22: 0.075 | C22: Compliant marketing fee, not per-patient kickback
A23: Hybrid revenue per booking (£) | B23: =B15*B22 -> 225

Sheet Monthly Engine
A1: 36-Month Engine — one ramp, three revenue models
A3: Month | B3: Yr | C3: Active clinics | D3: Total bookings | E3: Rev: Commission | F3: Rev: Subscription | G3: Rev: Hybrid | H3: Ops cost | I3: CAC | J3: Fixed opex | K3: Net: Commission | L3: Net: Subscription | M3: Net: Hybrid
A4: 1 | B4: =INT((A4-1)/12)+1 -> 1 | C4: =Assumptions!$B$5 -> 3 | D4: =C4*Assumptions!$B$7 -> 6 | E4: =D4*Assumptions!$B$17 -> 2700 | F4: =C4*Assumptions!$B$19 -> 1800 | G4: =C4*Assumptions!$B$21+D4*Assumptions!$B$23 -> 1950 | H4: =D4*Assumptions!$B$9 -> 360 | I4: =D4*Assumptions!$B$10 -> 900 | J4: =CHOOSE(B4,Assumptions!$B$11,Assumptions!$B$12,Assumptions!$B$13) -> 12000 | K4: =E4-H4-I4-J4 -> -10560 | L4: =F4-H4-I4-J4 -> -11460 | M4: =G4-H4-I4-J4 -> -11310
A5: 2 | B5: =INT((A5-1)/12)+1 -> 1 | C5: =C4+Assumptions!$B$6 -> 5 | D5: =C5*Assumptions!$B$7 -> 10 | E5: =D5*Assumptions!$B$17 -> 4500 | F5: =C5*Assumptions!$B$19 -> 3000 | G5: =C5*Assumptions!$B$21+D5*Assumptions!$B$23 -> 3250 | H5: =D5*Assumptions!$B$9 -> 600 | I5: =D5*Assumptions!$B$10 -> 1500 | J5: =CHOOSE(B5,Assumptions!$B$11,Assumptions!$B$12,Assumptions!$B$13) -> 12000 | K5: =E5-H5-I5-J5 -> -9600 | L5: =F5-H5-I5-J5 -> -11100 | M5: =G5-H5-I5-J5 -> -10850
A6: 3 | B6: =INT((A6-1)/12)+1 -> 1 | C6: =C5+Assumptions!$B$6 -> 7 | D6: =C6*Assumptions!$B$7 -> 14 | E6: =D6*Assumptions!$B$17 -> 6300 | F6: =C6*Assumptions!$B$19 -> 4200 | G6: =C6*Assumptions!$B$21+D6*Assumptions!$B$23 -> 4550 | H6: =D6*Assumptions!$B$9 -> 840 | I6: =D6*Assumptions!$B$10 -> 2100 | J6: =CHOOSE(B6,Assumptions!$B$11,Assumptions!$B$12,Assumptions!$B$13) -> 12000 | K6: =E6-H6-I6-J6 -> -8640 | L6: =F6-H6-I6-J6 -> -10740 | M6: =G6-H6-I6-J6 -> -10390
A7: 4 | B7: =INT((A7-1)/12)+1 -> 1 | C7: =C6+Assumptions!$B$6 -> 9 | D7: =C7*Assumptions!$B$7 -> 18 | E7: =D7*Assumptions!$B$17 -> 8100 | F7: =C7*Assumptions!$B$19 -> 5400 | G7: =C7*Assumptions!$B$21+D7*Assumptions!$B$23 -> 5850 | H7: =D7*Assumptions!$B$9 -> 1080 | I7: =D7*Assumptions!$B$10 -> 2700 | J7: =CHOOSE(B7,Assumptions!$B$11,Assumptions!$B$12,Assumptions!$B$13) -> 12000 | K7: =E7-H7-I7-J7 -> -7680 | L7: =F7-H7-I7-J7 -> -10380 | M7: =G7-H7-I7-J7 -> -9930
A8: 5 | B8: =INT((A8-1)/12)+1 -> 1 | C8: =C7+Assumptions!$B$6 -> 11 | D8: =C8*Assumptions!$B$7 -> 22 | E8: =D8*Assumptions!$B$17 -> 9900 | F8: =C8*Assumptions!$B$19 -> 6600 | G8: =C8*Assumptions!$B$21+D8*Assumptions!$B$23 -> 7150 | H8: =D8*Assumptions!$B$9 -> 1320 | I8: =D8*Assumptions!$B$10 -> 3300 | J8: =CHOOSE(B8,Assumptions!$B$11,Assumptions!$B$12,Assumptions!$B$13) -> 12000 | K8: =E8-H8-I8-J8 -> -6720 | L8: =F8-H8-I8-J8 -> -10020 | M8: =G8-H8-I8-J8 -> -9470
A9: 6 | B9: =INT((A9-1)/12)+1 -> 1 | C9: =C8+Assumptions!$B$6 -> 13 | D9: =C9*Assumptions!$B$7 -> 26 | E9: =D9*Assumptions!$B$17 -> 11700 | F9: =C9*Assumptions!$B$19 -> 7800 | G9: =C9*Assumptions!$B$21+D9*Assumptions!$B$23 -> 8450 | H9: =D9*Assumptions!$B$9 -> 1560 | I9: =D9*Assumptions!$B$10 -> 3900 | J9: =CHOOSE(B9,Assumptions!$B$11,Assumptions!$B$12,Assumptions!$B$13) -> 12000 | K9: =E9-H9-I9-J9 -> -5760 | L9: =F9-H9-I9-J9 -> -9660 | M9: =G9-H9-I9-J9 -> -9010
A10: 7 | B10: =INT((A10-1)/12)+1 -> 1 | C10: =C9+Assumptions!$B$6 -> 15 | D10: =C10*Assumptions!$B$7 -> 30 | E10: =D10*Assumptions!$B$17 -> 13500 | F10: =C10*Assumptions!$B$19 -> 9000 | G10: =C10*Assumptions!$B$21+D10*Assumptions!$B$23 -> 9750 | H10: =D10*Assumptions!$B$9 -> 1800 | I10: =D10*Assumptions!$B$10 -> 4500 | J10: =CHOOSE(B10,Assumptions!$B$11,Assumptions!$B$12,Assumptions!$B$13) -> 12000 | K10: =E10-H10-I10-J10 -> -4800 | L10: =F10-H10-I10-J10 -> -9300 | M10: =G10-H10-I10-J10 -> -8550
A11: 8 | B11: =INT((A11-1)/12)+1 -> 1 | C11: =C10+Assumptions!$B$6 -> 17 | D11: =C11*Assumptions!$B$7 -> 34 | E11: =D11*Assumptions!$B$17 -> 15300 | F11: =C11*Assumptions!$B$19 -> 10200 | G11: =C11*Assumptions!$B$21+D11*Assumptions!$B$23 -> 11050 | H11: =D11*Assumptions!$B$9 -> 2040 | I11: =D11*Assumptions!$B$10 -> 5100 | J11: =CHOOSE(B11,Assumptions!$B$11,Assumptions!$B$12,Assumptions!$B$13) -> 12000 | K11: =E11-H11-I11-J11 -> -3840 | L11: =F11-H11-I11-J11 -> -8940 | M11: =G11-H11-I11-J11 -> -8090
A12: 9 | B12: =INT((A12-1)/12)+1 -> 1 | C12: =C11+Assumptions!$B$6 -> 19 | D12: =C12*Assumptions!$B$7 -> 38 | E12: =D12*Assumptions!$B$17 -> 17100 | F12: =C12*Assumptions!$B$19 -> 11400 | G12: =C12*Assumptions!$B$21+D12*Assumptions!$B$23 -> 12350 | H12: =D12*Assumptions!$B$9 -> 2280 | I12: =D12*Assumptions!$B$10 -> 5700 | J12: =CHOOSE(B12,Assumptions!$B$11,Assumptions!$B$12,Assumptions!$B$13) -> 12000 | K12: =E12-H12-I12-J12 -> -2880 | L12: =F12-H12-I12-J12 -> -8580 | M12: =G12-H12-I12-J12 -> -7630
A13: 10 | B13: =INT((A13-1)/12)+1 -> 1 | C13: =C12+Assumptions!$B$6 -> 21 | D13: =C13*Assumptions!$B$7 -> 42 | E13: =D13*Assumptions!$B$17 -> 18900 | F13: =C13*Assumptions!$B$19 -> 12600 | G13: =C13*Assumptions!$B$21+D13*Assumptions!$B$23 -> 13650 | H13: =D13*Assumptions!$B$9 -> 2520 | I13: =D13*Assumptions!$B$10 -> 6300 | J13: =CHOOSE(B13,Assumptions!$B$11,Assumptions!$B$12,Assumptions!$B$13) -> 12000 | K13: =E13-H13-I13-J13 -> -1920 | L13: =F13-H13-I13-J13 -> -8220 | M13: =G13-H13-I13-J13 -> -7170
A14: 11 | B14: =INT((A14-1)/12)+1 -> 1 | C14: =C13+Assumptions!$B$6 -> 23 | D14: =C14*Assumptions!$B$7 -> 46 | E14: =D14*Assumptions!$B$17 -> 20700 | F14: =C14*Assumptions!$B$19 -> 13800 | G14: =C14*Assumptions!$B$21+D14*Assumptions!$B$23 -> 14950 | H14: =D14*Assumptions!$B$9 -> 2760 | I14: =D14*Assumptions!$B$10 -> 6900 | J14: =CHOOSE(B14,Assumptions!$B$11,Assumptions!$B$12,Assumptions!$B$13) -> 12000 | K14: =E14-H14-I14-J14 -> -960 | L14: =F14-H14-I14-J14 -> -7860 | M14: =G14-H14-I14-J14 -> -6710
A15: 12 | B15: =INT((A15-1)/12)+1 -> 1 | C15: =C14+Assumptions!$B$6 -> 25 | D15: =C15*Assumptions!$B$7 -> 50 | E15: =D15*Assumptions!$B$17 -> 22500 | F15: =C15*Assumptions!$B$19 -> 15000 | G15: =C15*Assumptions!$B$21+D15*Assumptions!$B$23 -> 16250 | H15: =D15*Assumptions!$B$9 -> 3000 | I15: =D15*Assumptions!$B$10 -> 7500 | J15: =CHOOSE(B15,Assumptions!$B$11,Assumptions!$B$12,Assumptions!$B$13) -> 12000 | K15: =E15-H15-I15-J15 -> 0 | L15: =F15-H15-I15-J15 -> -7500 | M15: =G15-H15-I15-J15 -> -6250
A16: 13 | B16: =INT((A16-1)/12)+1 -> 2 | C16: =C15+Assumptions!$B$6 -> 27 | D16: =C16*Assumptions!$B$7 -> 54 | E16: =D16*Assumptions!$B$17 -> 24300 | F16: =C16*Assumptions!$B$19 -> 16200 | G16: =C16*Assumptions!$B$21+D16*Assumptions!$B$23 -> 17550 | H16: =D16*Assumptions!$B$9 -> 3240 | I16: =D16*Assumptions!$B$10 -> 8100 | J16: =CHOOSE(B16,Assumptions!$B$11,Assumptions!$B$12,Assumptions!$B$13) -> 22000 | K16: =E16-H16-I16-J16 -> -9040 | L16: =F16-H16-I16-J16 -> -17140 | M16: =G16-H16-I16-J16 -> -15790
... A39: 36 | B39: =INT((A39-1)/12)+1 -> 3 | C39: =C38+Assumptions!$B$6 -> 73 | D39: =C39*Assumptions!$B$7 -> 146 | E39: =D39*Assumptions!$B$17 -> 65700 | F39: =C39*Assumptions!$B$19 -> 43800 | G39: =C39*Assumptions!$B$21+D39*Assumptions!$B$23 -> 47450 | H39: =D39*Assumptions!$B$9 -> 8760 | I39: =D39*Assumptions!$B$10 -> 21900 | J39: =CHOOSE(B39,Assumptions!$B$11,Assumptions!$B$12,Assumptions!$B$13) -> 32000 | K39: =E39-H39-I39-J39 -> 3040 | L39: =F39-H39-I39-J39 -> -18860 | M39: =G39-H39-I39-J39 -> -15210

Sheet Comparison
A1: NAIA — Business Model Comparison
A2: Commission vs Subscription vs Hybrid · identical clinic/booking ramp & cost base
A4: REVENUE (£)
A5: Model | B5: Year 1 | C5: Year 2 | D5: Year 3 | E5: 3-yr total | F5: Y3 exit run-rate /mo
A6: Commission | B6: =SUMIF('Monthly Engine'!$B$4:$B$39,1,'Monthly Engine'!$E$4:$E$39) -> 151200 | C6: =SUMIF('Monthly Engine'!$B$4:$B$39,2,'Monthly Engine'!$E$4:$E$39) -> 410400 | D6: =SUMIF('Monthly Engine'!$B$4:$B$39,3,'Monthly Engine'!$E$4:$E$39) -> 669600 | E6: =SUM(B6:D6) -> 1231200 | F6: ='Monthly Engine'!E39 -> 65700
A7: Subscription | B7: =SUMIF('Monthly Engine'!$B$4:$B$39,1,'Monthly Engine'!$F$4:$F$39) -> 100800 | C7: =SUMIF('Monthly Engine'!$B$4:$B$39,2,'Monthly Engine'!$F$4:$F$39) -> 273600 | D7: =SUMIF('Monthly Engine'!$B$4:$B$39,3,'Monthly Engine'!$F$4:$F$39) -> 446400 | E7: =SUM(B7:D7) -> 820800 | F7: ='Monthly Engine'!F39 -> 43800
A8: Hybrid | B8: =SUMIF('Monthly Engine'!$B$4:$B$39,1,'Monthly Engine'!$G$4:$G$39) -> 109200 | C8: =SUMIF('Monthly Engine'!$B$4:$B$39,2,'Monthly Engine'!$G$4:$G$39) -> 296400 | D8: =SUMIF('Monthly Engine'!$B$4:$B$39,3,'Monthly Engine'!$G$4:$G$39) -> 483600 | E8: =SUM(B8:D8) -> 889200 | F8: ='Monthly Engine'!G39 -> 47450
A11: NET PROFIT (£) — same cost base
A12: Model | B12: Year 1 | C12: Year 2 | D12: Year 3 | E12: 3-yr total | F12: Y3 exit run-rate /mo
A13: Commission | B13: =SUMIF('Monthly Engine'!$B$4:$B$39,1,'Monthly Engine'!$K$4:$K$39) -> -63360 | C13: =SUMIF('Monthly Engine'!$B$4:$B$39,2,'Monthly Engine'!$K$4:$K$39) -> -45120 | D13: =SUMIF('Monthly Engine'!$B$4:$B$39,3,'Monthly Engine'!$K$4:$K$39) -> -26880 | E13: =SUM(B13:D13) -> -135360 | F13: ='Monthly Engine'!K39 -> 3040
A14: Subscription | B14: =SUMIF('Monthly Engine'!$B$4:$B$39,1,'Monthly Engine'!$L$4:$L$39) -> -113760 | C14: =SUMIF('Monthly Engine'!$B$4:$B$39,2,'Monthly Engine'!$L$4:$L$39) -> -181920 | D14: =SUMIF('Monthly Engine'!$B$4:$B$39,3,'Monthly Engine'!$L$4:$L$39) -> -250080 | E14: =SUM(B14:D14) -> -545760 | F14: ='Monthly Engine'!L39 -> -18860
A15: Hybrid | B15: =SUMIF('Monthly Engine'!$B$4:$B$39,1,'Monthly Engine'!$M$4:$M$39) -> -105360 | C15: =SUMIF('Monthly Engine'!$B$4:$B$39,2,'Monthly Engine'!$M$4:$M$39) -> -159120 | D15: =SUMIF('Monthly Engine'!$B$4:$B$39,3,'Monthly Engine'!$M$4:$M$39) -> -212880 | E15: =SUM(B15:D15) -> -477360 | F15: ='Monthly Engine'!M39 -> -15210
A18: BEYOND THE NUMBERS
A19: Factor | B19: Commission | C19: Subscription | D19: Hybrid
A20: Revenue potential | B20: High | C20: Lower | D20: Medium-High
A21: Revenue predictability | B21: Low (transactional) | C21: High (recurring) | D21: Medium-High
A22: Regulatory risk (patient referral) | B22: Higher | C22: Lowest | D22: Low-Medium
A23: Fit with NAIA trust brand | B23: Good | C23: Weaker (pay-for-placement) | D23: Good
A24: Ease of selling to clinics | B24: Harder (share upside) | C24: Easier (fixed cost) | D24: Medium
A25: Investor appeal | B25: GMV story | C25: SaaS multiple | D25: Balanced
A27: Note: costs held identical across models to isolate the revenue effect. In a real subscription model some demand-gen (CAC) shifts to clinics, improving its net. Not legal advice — confirm patient-referral rules per market.
A30: Model | B30: 3-yr revenue | C30: 3-yr net
A31: Commission | B31: =E6 -> 1231200 | C31: =E13 -> -135360
A32: Subscription | B32: =E7 -> 820800 | C32: =E14 -> -545760
A33: Hybrid | B33: =E8 -> 889200 | C33: =E15 -> -477360
